cdkgithub/__init__.py
cdkgithub/py.typed
cdkgithub/_jsii/__init__.py
cdkgithub/_jsii/cdk-github@0.0.57.jsii.tgz
cdk_github-0.0.57.dist-info/LICENSE
cdk_github-0.0.57.dist-info/METADATA
cdk_github-0.0.57.dist-info/WHEEL
cdk_github-0.0.57.dist-info/top_level.txt
cdk_github-0.0.57.dist-info/RECORD
