Metadata-Version: 2.1
Name: cdk-github
Version: 0.0.57
Summary: AWS CDK Construct Library to interact with GitHub's API.
Home-page: https://github.com/WtfJoke/cdk-github
Author: Manuel
License: MIT
Project-URL: Source, https://github.com/WtfJoke/cdk-github
Classifier: Intended Audience :: Developers
Classifier: Operating System :: OS Independent
Classifier: Programming Language :: JavaScript
Classifier: Programming Language :: Python :: 3 :: Only
Classifier: Programming Language :: Python :: 3.8
Classifier: Programming Language :: Python :: 3.9
Classifier: Programming Language :: Python :: 3.10
Classifier: Programming Language :: Python :: 3.11
Classifier: Typing :: Typed
Classifier: Development Status :: 4 - Beta
Classifier: License :: OSI Approved
Requires-Python: ~=3.8
License-File: LICENSE
Requires-Dist: aws-cdk-lib <3.0.0,>=2.25.0
Requires-Dist: constructs <11.0.0,>=10.0.5
Requires-Dist: jsii <2.0.0,>=1.101.0
Requires-Dist: publication >=0.0.3
Requires-Dist: typeguard ~=2.13.3
